{
  "season": 2025,
  "round": 21,
  "matches": [
    {
      "id": "1379178",
      "league": "Premier League",
      "venue": "London Stadium",
      "attendance": null,
      "kickoff": "2026-01-06T20:00:00+00:00",
      "homeTeamId": "west-ham",
      "awayTeamId": "nottingham-forest",
      "score": {
        "home": 1,
        "away": 2
      },
      "status": {
        "state": "FT",
        "halfTimeScore": "1–0"
      },
      "events": [
        {
          "id": "1379178-0",
          "minute": "13'",
          "team": "home",
          "kind": "own-goal",
          "player": "Murillo",
          "assist": "",
          "detail": "og",
          "rawType": "Goal",
          "rawDetail": "Own Goal",
          "elapsed": 13,
          "extra": 0
        },
        {
          "id": "1379178-1",
          "minute": "46'",
          "team": "away",
          "kind": "sub",
          "player": "O. Hutchinson",
          "assist": "D. Bakwa",
          "inPlayer": "D. Bakwa",
          "outPlayer": "O. Hutchinson",
          "detail": "",
          "rawType": "subst",
          "rawDetail": "Substitution 1",
          "elapsed": 46,
          "extra": 0
        },
        {
          "id": "1379178-2",
          "minute": "52'",
          "team": "home",
          "kind": "var-goal-cancelled",
          "player": "Crysencio Summerville",
          "assist": "",
          "detail": "",
          "rawType": "Var",
          "rawDetail": "Goal cancelled",
          "elapsed": 52,
          "extra": 0
        },
        {
          "id": "1379178-3",
          "minute": "55'",
          "team": "away",
          "kind": "goal",
          "player": "N. Dominguez",
          "assist": "E. Anderson",
          "detail": "",
          "rawType": "Goal",
          "rawDetail": "Normal Goal",
          "elapsed": 55,
          "extra": 0
        },
        {
          "id": "1379178-4",
          "minute": "61'",
          "team": "home",
          "kind": "yellow",
          "player": "Jean-Clair Todibo",
          "assist": "",
          "detail": "",
          "rawType": "Card",
          "rawDetail": "Yellow Card",
          "elapsed": 61,
          "extra": 0
        },
        {
          "id": "1379178-5",
          "minute": "63'",
          "team": "home",
          "kind": "sub",
          "player": "Lucas Paqueta",
          "assist": "Pablo",
          "inPlayer": "Pablo",
          "outPlayer": "Lucas Paqueta",
          "detail": "",
          "rawType": "subst",
          "rawDetail": "Substitution 1",
          "elapsed": 63,
          "extra": 0
        },
        {
          "id": "1379178-6",
          "minute": "63'",
          "team": "home",
          "kind": "sub",
          "player": "O. Scarles",
          "assist": "E. Mayers",
          "inPlayer": "E. Mayers",
          "outPlayer": "O. Scarles",
          "detail": "",
          "rawType": "subst",
          "rawDetail": "Substitution 2",
          "elapsed": 63,
          "extra": 0
        },
        {
          "id": "1379178-7",
          "minute": "80'",
          "team": "home",
          "kind": "sub",
          "player": "M. Fernandes",
          "assist": "F. Potts",
          "inPlayer": "F. Potts",
          "outPlayer": "M. Fernandes",
          "detail": "",
          "rawType": "subst",
          "rawDetail": "Substitution 3",
          "elapsed": 80,
          "extra": 0
        },
        {
          "id": "1379178-8",
          "minute": "86'",
          "team": "away",
          "kind": "var-pen-confirmed",
          "player": "Morgan Gibbs-White",
          "assist": "",
          "detail": "",
          "rawType": "Var",
          "rawDetail": "Penalty confirmed",
          "elapsed": 86,
          "extra": 0
        },
        {
          "id": "1379178-9",
          "minute": "89'",
          "team": "away",
          "kind": "goal",
          "player": "M. Gibbs-White",
          "assist": "",
          "detail": "pen",
          "rawType": "Goal",
          "rawDetail": "Penalty",
          "elapsed": 89,
          "extra": 0
        },
        {
          "id": "1379178-10",
          "minute": "90'+6",
          "team": "home",
          "kind": "yellow",
          "player": "Konstantinos Mavropanos",
          "assist": "",
          "detail": "",
          "rawType": "Card",
          "rawDetail": "Yellow Card",
          "elapsed": 90,
          "extra": 6
        },
        {
          "id": "1379178-11",
          "minute": "90'+4",
          "team": "home",
          "kind": "yellow",
          "player": "Kyle Walker-Peters",
          "assist": "",
          "detail": "",
          "rawType": "Card",
          "rawDetail": "Yellow Card",
          "elapsed": 90,
          "extra": 4
        },
        {
          "id": "1379178-12",
          "minute": "90'+2",
          "team": "away",
          "kind": "sub",
          "player": "",
          "assist": "Morato",
          "inPlayer": "Morato",
          "outPlayer": "",
          "detail": "",
          "rawType": "subst",
          "rawDetail": "Substitution 2",
          "elapsed": 90,
          "extra": 2
        }
      ]
    },
    {
      "id": "1379170",
      "league": "Premier League",
      "venue": "Vitality Stadium",
      "attendance": null,
      "kickoff": "2026-01-07T19:30:00+00:00",
      "homeTeamId": "bournemouth",
      "awayTeamId": "tottenham",
      "score": {
        "home": 3,
        "away": 2
      },
      "status": {
        "state": "FT",
        "halfTimeScore": "2–1"
      },
      "events": [
        {
          "id": "1379170-0",
          "minute": "5'",
          "team": "away",
          "kind": "goal",
          "player": "M. Tel",
          "assist": "X. Simons",
          "detail": "",
          "rawType": "Goal",
          "rawDetail": "Normal Goal",
          "elapsed": 5,
          "extra": 0
        },
        {
          "id": "1379170-1",
          "minute": "22'",
          "team": "home",
          "kind": "goal",
          "player": "Evanilson",
          "assist": "M. Tavernier",
          "detail": "",
          "rawType": "Goal",
          "rawDetail": "Normal Goal",
          "elapsed": 22,
          "extra": 0
        },
        {
          "id": "1379170-2",
          "minute": "36'",
          "team": "home",
          "kind": "goal",
          "player": "E. J. Kroupi",
          "assist": "M. Senesi",
          "detail": "",
          "rawType": "Goal",
          "rawDetail": "Normal Goal",
          "elapsed": 36,
          "extra": 0
        },
        {
          "id": "1379170-3",
          "minute": "43'",
          "team": "home",
          "kind": "yellow",
          "player": "Antoine Semenyo",
          "assist": "",
          "detail": "",
          "rawType": "Card",
          "rawDetail": "Yellow Card",
          "elapsed": 43,
          "extra": 0
        },
        {
          "id": "1379170-4",
          "minute": "51'",
          "team": "home",
          "kind": "yellow",
          "player": "Lewis Cook",
          "assist": "",
          "detail": "",
          "rawType": "Card",
          "rawDetail": "Yellow Card",
          "elapsed": 51,
          "extra": 0
        },
        {
          "id": "1379170-5",
          "minute": "57'",
          "team": "away",
          "kind": "sub",
          "player": "L. Bergvall",
          "assist": "W. Odobert",
          "inPlayer": "W. Odobert",
          "outPlayer": "L. Bergvall",
          "detail": "",
          "rawType": "subst",
          "rawDetail": "Substitution 1",
          "elapsed": 57,
          "extra": 0
        },
        {
          "id": "1379170-6",
          "minute": "60'",
          "team": "away",
          "kind": "yellow",
          "player": "Pedro Porro",
          "assist": "",
          "detail": "",
          "rawType": "Card",
          "rawDetail": "Yellow Card",
          "elapsed": 60,
          "extra": 0
        },
        {
          "id": "1379170-7",
          "minute": "61'",
          "team": "away",
          "kind": "yellow",
          "player": "Randal Kolo Muani",
          "assist": "",
          "detail": "",
          "rawType": "Card",
          "rawDetail": "Yellow Card",
          "elapsed": 61,
          "extra": 0
        },
        {
          "id": "1379170-8",
          "minute": "64'",
          "team": "home",
          "kind": "sub",
          "player": "E. J. Kroupi",
          "assist": "D. Brooks",
          "inPlayer": "D. Brooks",
          "outPlayer": "E. J. Kroupi",
          "detail": "",
          "rawType": "subst",
          "rawDetail": "Substitution 1",
          "elapsed": 64,
          "extra": 0
        },
        {
          "id": "1379170-9",
          "minute": "64'",
          "team": "home",
          "kind": "sub",
          "player": "Evanilson",
          "assist": "E. Unal",
          "inPlayer": "E. Unal",
          "outPlayer": "Evanilson",
          "detail": "",
          "rawType": "subst",
          "rawDetail": "Substitution 2",
          "elapsed": 64,
          "extra": 0
        },
        {
          "id": "1379170-10",
          "minute": "67'",
          "team": "away",
          "kind": "sub",
          "player": "R. Kolo Muani",
          "assist": "Richarlison",
          "inPlayer": "Richarlison",
          "outPlayer": "R. Kolo Muani",
          "detail": "",
          "rawType": "subst",
          "rawDetail": "Substitution 2",
          "elapsed": 67,
          "extra": 0
        },
        {
          "id": "1379170-11",
          "minute": "73'",
          "team": "away",
          "kind": "var-pen-cancelled",
          "player": "Micky van de Ven",
          "assist": "",
          "detail": "",
          "rawType": "Var",
          "rawDetail": "Penalty cancelled",
          "elapsed": 73,
          "extra": 0
        },
        {
          "id": "1379170-12",
          "minute": "75'",
          "team": "away",
          "kind": "yellow",
          "player": "Micky van de Ven",
          "assist": "",
          "detail": "",
          "rawType": "Card",
          "rawDetail": "Yellow Card",
          "elapsed": 75,
          "extra": 0
        },
        {
          "id": "1379170-13",
          "minute": "77'",
          "team": "home",
          "kind": "yellow",
          "player": "Álex Jiménez",
          "assist": "",
          "detail": "",
          "rawType": "Card",
          "rawDetail": "Yellow Card",
          "elapsed": 77,
          "extra": 0
        },
        {
          "id": "1379170-14",
          "minute": "78'",
          "team": "away",
          "kind": "goal",
          "player": "J. Palhinha",
          "assist": "",
          "detail": "",
          "rawType": "Goal",
          "rawDetail": "Normal Goal",
          "elapsed": 78,
          "extra": 0
        },
        {
          "id": "1379170-15",
          "minute": "86'",
          "team": "away",
          "kind": "sub",
          "player": "R. Bentancur",
          "assist": "A. Gray",
          "inPlayer": "A. Gray",
          "outPlayer": "R. Bentancur",
          "detail": "",
          "rawType": "subst",
          "rawDetail": "Substitution 3",
          "elapsed": 86,
          "extra": 0
        },
        {
          "id": "1379170-16",
          "minute": "87'",
          "team": "home",
          "kind": "sub",
          "player": "M. Tavernier",
          "assist": "B. Diakite",
          "inPlayer": "B. Diakite",
          "outPlayer": "M. Tavernier",
          "detail": "",
          "rawType": "subst",
          "rawDetail": "Substitution 3",
          "elapsed": 87,
          "extra": 0
        },
        {
          "id": "1379170-17",
          "minute": "87'",
          "team": "home",
          "kind": "sub",
          "player": "A. Jimenez",
          "assist": "A. Adli",
          "inPlayer": "A. Adli",
          "outPlayer": "A. Jimenez",
          "detail": "",
          "rawType": "subst",
          "rawDetail": "Substitution 4",
          "elapsed": 87,
          "extra": 0
        },
        {
          "id": "1379170-18",
          "minute": "90'+10",
          "team": "home",
          "kind": "sub",
          "player": "A. Semenyo",
          "assist": "V. Milosavljevic",
          "inPlayer": "V. Milosavljevic",
          "outPlayer": "A. Semenyo",
          "detail": "",
          "rawType": "subst",
          "rawDetail": "Substitution 5",
          "elapsed": 90,
          "extra": 10
        },
        {
          "id": "1379170-19",
          "minute": "90'",
          "team": "home",
          "kind": "goal",
          "player": "A. Semenyo",
          "assist": "D. Brooks",
          "detail": "",
          "rawType": "Goal",
          "rawDetail": "Normal Goal",
          "elapsed": 90,
          "extra": 0
        }
      ]
    },
    {
      "id": "1379175",
      "league": "Premier League",
      "venue": "Craven Cottage",
      "attendance": null,
      "kickoff": "2026-01-07T19:30:00+00:00",
      "homeTeamId": "fulham",
      "awayTeamId": "chelsea",
      "score": {
        "home": 2,
        "away": 1
      },
      "status": {
        "state": "FT",
        "halfTimeScore": "0–0"
      },
      "events": [
        {
          "id": "1379175-0",
          "minute": "22'",
          "team": "away",
          "kind": "red",
          "player": "Marc Cucurella",
          "assist": "",
          "detail": "",
          "rawType": "Card",
          "rawDetail": "Red Card",
          "elapsed": 22,
          "extra": 0
        },
        {
          "id": "1379175-1",
          "minute": "24'",
          "team": "away",
          "kind": "yellow",
          "player": "Enzo Fernández",
          "assist": "",
          "detail": "",
          "rawType": "Card",
          "rawDetail": "Yellow Card",
          "elapsed": 24,
          "extra": 0
        },
        {
          "id": "1379175-2",
          "minute": "25'",
          "team": "away",
          "kind": "yellow",
          "player": "Cole Palmer",
          "assist": "",
          "detail": "",
          "rawType": "Card",
          "rawDetail": "Yellow Card",
          "elapsed": 25,
          "extra": 0
        },
        {
          "id": "1379175-3",
          "minute": "25'",
          "team": "away",
          "kind": "yellow",
          "player": "Tosin Adarabioyo",
          "assist": "",
          "detail": "",
          "rawType": "Card",
          "rawDetail": "Yellow Card",
          "elapsed": 25,
          "extra": 0
        },
        {
          "id": "1379175-4",
          "minute": "28'",
          "team": "away",
          "kind": "sub",
          "player": "Andrey Santos",
          "assist": "J. Hato",
          "inPlayer": "J. Hato",
          "outPlayer": "Andrey Santos",
          "detail": "",
          "rawType": "subst",
          "rawDetail": "Substitution 1",
          "elapsed": 28,
          "extra": 0
        },
        {
          "id": "1379175-5",
          "minute": "45'+7",
          "team": "home",
          "kind": "yellow",
          "player": "Jorge Cuenca",
          "assist": "",
          "detail": "",
          "rawType": "Card",
          "rawDetail": "Yellow Card",
          "elapsed": 45,
          "extra": 7
        },
        {
          "id": "1379175-6",
          "minute": "45'+5",
          "team": "home",
          "kind": "var-goal-cancelled",
          "player": "Harry Wilson",
          "assist": "",
          "detail": "",
          "rawType": "Var",
          "rawDetail": "Goal cancelled",
          "elapsed": 45,
          "extra": 5
        },
        {
          "id": "1379175-7",
          "minute": "46'",
          "team": "home",
          "kind": "sub",
          "player": "J. Cuenca",
          "assist": "Kevin",
          "inPlayer": "Kevin",
          "outPlayer": "J. Cuenca",
          "detail": "",
          "rawType": "subst",
          "rawDetail": "Substitution 1",
          "elapsed": 46,
          "extra": 0
        },
        {
          "id": "1379175-8",
          "minute": "55'",
          "team": "home",
          "kind": "goal",
          "player": "R. Jimenez",
          "assist": "S. Berge",
          "detail": "",
          "rawType": "Goal",
          "rawDetail": "Normal Goal",
          "elapsed": 55,
          "extra": 0
        },
        {
          "id": "1379175-9",
          "minute": "65'",
          "team": "away",
          "kind": "sub",
          "player": "E. Fernandez",
          "assist": "R. James",
          "inPlayer": "R. James",
          "outPlayer": "E. Fernandez",
          "detail": "",
          "rawType": "subst",
          "rawDetail": "Substitution 2",
          "elapsed": 65,
          "extra": 0
        },
        {
          "id": "1379175-10",
          "minute": "72'",
          "team": "away",
          "kind": "goal",
          "player": "L. Delap",
          "assist": "",
          "detail": "",
          "rawType": "Goal",
          "rawDetail": "Normal Goal",
          "elapsed": 72,
          "extra": 0
        },
        {
          "id": "1379175-11",
          "minute": "73'",
          "team": "home",
          "kind": "sub",
          "player": "A. Robinson",
          "assist": "R. Sessegnon",
          "inPlayer": "R. Sessegnon",
          "outPlayer": "A. Robinson",
          "detail": "",
          "rawType": "subst",
          "rawDetail": "Substitution 2",
          "elapsed": 73,
          "extra": 0
        },
        {
          "id": "1379175-12",
          "minute": "73'",
          "team": "home",
          "kind": "sub",
          "player": "T. Cairney",
          "assist": "S. Lukic",
          "inPlayer": "S. Lukic",
          "outPlayer": "T. Cairney",
          "detail": "",
          "rawType": "subst",
          "rawDetail": "Substitution 3",
          "elapsed": 73,
          "extra": 0
        },
        {
          "id": "1379175-13",
          "minute": "75'",
          "team": "away",
          "kind": "sub",
          "player": "C. Palmer",
          "assist": "Joao Pedro",
          "inPlayer": "Joao Pedro",
          "outPlayer": "C. Palmer",
          "detail": "",
          "rawType": "subst",
          "rawDetail": "Substitution 3",
          "elapsed": 75,
          "extra": 0
        },
        {
          "id": "1379175-14",
          "minute": "76'",
          "team": "away",
          "kind": "sub",
          "player": "M. Gusto",
          "assist": "J. Acheampong",
          "inPlayer": "J. Acheampong",
          "outPlayer": "M. Gusto",
          "detail": "",
          "rawType": "subst",
          "rawDetail": "Substitution 4",
          "elapsed": 76,
          "extra": 0
        },
        {
          "id": "1379175-15",
          "minute": "78'",
          "team": "home",
          "kind": "yellow",
          "player": "Timothy Castagne",
          "assist": "",
          "detail": "",
          "rawType": "Card",
          "rawDetail": "Yellow Card",
          "elapsed": 78,
          "extra": 0
        },
        {
          "id": "1379175-16",
          "minute": "81'",
          "team": "home",
          "kind": "goal",
          "player": "H. Wilson",
          "assist": "",
          "detail": "",
          "rawType": "Goal",
          "rawDetail": "Normal Goal",
          "elapsed": 81,
          "extra": 0
        },
        {
          "id": "1379175-17",
          "minute": "83'",
          "team": "home",
          "kind": "sub",
          "player": "E. Smith Rowe",
          "assist": "H. Reed",
          "inPlayer": "H. Reed",
          "outPlayer": "E. Smith Rowe",
          "detail": "",
          "rawType": "subst",
          "rawDetail": "Substitution 4",
          "elapsed": 83,
          "extra": 0
        },
        {
          "id": "1379175-18",
          "minute": "90'",
          "team": "home",
          "kind": "yellow",
          "player": "Raúl Jiménez",
          "assist": "",
          "detail": "",
          "rawType": "Card",
          "rawDetail": "Yellow Card",
          "elapsed": 90,
          "extra": 0
        },
        {
          "id": "1379175-19",
          "minute": "90'+1",
          "team": "home",
          "kind": "sub",
          "player": "H. Wilson",
          "assist": "A. Traore",
          "inPlayer": "A. Traore",
          "outPlayer": "H. Wilson",
          "detail": "",
          "rawType": "subst",
          "rawDetail": "Substitution 5",
          "elapsed": 90,
          "extra": 1
        }
      ]
    },
    {
      "id": "1379174",
      "league": "Premier League",
      "venue": "Hill Dickinson Stadium",
      "attendance": null,
      "kickoff": "2026-01-07T19:30:00+00:00",
      "homeTeamId": "everton",
      "awayTeamId": "wolves",
      "score": {
        "home": 1,
        "away": 1
      },
      "status": {
        "state": "FT",
        "halfTimeScore": "1–0"
      },
      "events": [
        {
          "id": "1379174-0",
          "minute": "17'",
          "team": "home",
          "kind": "goal",
          "player": "M. Keane",
          "assist": "T. Iroegbunam",
          "detail": "",
          "rawType": "Goal",
          "rawDetail": "Normal Goal",
          "elapsed": 17,
          "extra": 0
        },
        {
          "id": "1379174-1",
          "minute": "43'",
          "team": "away",
          "kind": "yellow",
          "player": "José Sá",
          "assist": "",
          "detail": "",
          "rawType": "Card",
          "rawDetail": "Yellow Card",
          "elapsed": 43,
          "extra": 0
        },
        {
          "id": "1379174-2",
          "minute": "46'",
          "team": "away",
          "kind": "sub",
          "player": "J. Arias",
          "assist": "Andre",
          "inPlayer": "Andre",
          "outPlayer": "J. Arias",
          "detail": "",
          "rawType": "subst",
          "rawDetail": "Substitution 1",
          "elapsed": 46,
          "extra": 0
        },
        {
          "id": "1379174-3",
          "minute": "57'",
          "team": "away",
          "kind": "yellow",
          "player": "Yerson Mosquera",
          "assist": "",
          "detail": "",
          "rawType": "Card",
          "rawDetail": "Yellow Card",
          "elapsed": 57,
          "extra": 0
        },
        {
          "id": "1379174-4",
          "minute": "67'",
          "team": "away",
          "kind": "sub",
          "player": "L. Krejci",
          "assist": "J. S. Larsen",
          "inPlayer": "J. S. Larsen",
          "outPlayer": "L. Krejci",
          "detail": "",
          "rawType": "subst",
          "rawDetail": "Substitution 2",
          "elapsed": 67,
          "extra": 0
        },
        {
          "id": "1379174-5",
          "minute": "69'",
          "team": "away",
          "kind": "goal",
          "player": "M. Mane",
          "assist": "J. S. Larsen",
          "detail": "",
          "rawType": "Goal",
          "rawDetail": "Normal Goal",
          "elapsed": 69,
          "extra": 0
        },
        {
          "id": "1379174-6",
          "minute": "77'",
          "team": "home",
          "kind": "yellow",
          "player": "Tim Iroegbunam",
          "assist": "",
          "detail": "",
          "rawType": "Card",
          "rawDetail": "Yellow Card",
          "elapsed": 77,
          "extra": 0
        },
        {
          "id": "1379174-7",
          "minute": "77'",
          "team": "away",
          "kind": "yellow",
          "player": "Hee-Chan Hwang",
          "assist": "",
          "detail": "",
          "rawType": "Card",
          "rawDetail": "Yellow Card",
          "elapsed": 77,
          "extra": 0
        },
        {
          "id": "1379174-8",
          "minute": "81'",
          "team": "home",
          "kind": "var-card-upgrade",
          "player": "Michael Keane",
          "assist": "",
          "detail": "",
          "rawType": "Var",
          "rawDetail": "Card upgrade",
          "elapsed": 81,
          "extra": 0
        },
        {
          "id": "1379174-9",
          "minute": "83'",
          "team": "home",
          "kind": "red",
          "player": "Michael Keane",
          "assist": "",
          "detail": "",
          "rawType": "Card",
          "rawDetail": "Red Card",
          "elapsed": 83,
          "extra": 0
        },
        {
          "id": "1379174-10",
          "minute": "87'",
          "team": "home",
          "kind": "yellow",
          "player": "Jack Grealish",
          "assist": "",
          "detail": "",
          "rawType": "Card",
          "rawDetail": "Yellow Card",
          "elapsed": 87,
          "extra": 0
        },
        {
          "id": "1379174-11",
          "minute": "87'",
          "team": "home",
          "kind": "sub",
          "player": "H. Armstrong",
          "assist": "N. Patterson",
          "inPlayer": "N. Patterson",
          "outPlayer": "H. Armstrong",
          "detail": "",
          "rawType": "subst",
          "rawDetail": "Substitution 1",
          "elapsed": 87,
          "extra": 0
        },
        {
          "id": "1379174-12",
          "minute": "87'",
          "team": "home",
          "kind": "sub",
          "player": "T. Barry",
          "assist": "Beto",
          "inPlayer": "Beto",
          "outPlayer": "T. Barry",
          "detail": "",
          "rawType": "subst",
          "rawDetail": "Substitution 2",
          "elapsed": 87,
          "extra": 0
        },
        {
          "id": "1379174-13",
          "minute": "90'",
          "team": "home",
          "kind": "yellow",
          "player": "Jack Grealish",
          "assist": "",
          "detail": "",
          "rawType": "Card",
          "rawDetail": "Yellow Card",
          "elapsed": 90,
          "extra": 0
        },
        {
          "id": "1379174-14",
          "minute": "90'",
          "team": "home",
          "kind": "red",
          "player": "Jack Grealish",
          "assist": "",
          "detail": "",
          "rawType": "Card",
          "rawDetail": "Red Card",
          "elapsed": 90,
          "extra": 0
        },
        {
          "id": "1379174-15",
          "minute": "90'+1",
          "team": "home",
          "kind": "sub",
          "player": "D. McNeil",
          "assist": "M. Rohl",
          "inPlayer": "M. Rohl",
          "outPlayer": "D. McNeil",
          "detail": "",
          "rawType": "subst",
          "rawDetail": "Substitution 3",
          "elapsed": 90,
          "extra": 1
        },
        {
          "id": "1379174-16",
          "minute": "90'+5",
          "team": "away",
          "kind": "sub",
          "player": "Hwang Hee-Chan",
          "assist": "Pedro Lima",
          "inPlayer": "Pedro Lima",
          "outPlayer": "Hwang Hee-Chan",
          "detail": "",
          "rawType": "subst",
          "rawDetail": "Substitution 3",
          "elapsed": 90,
          "extra": 5
        }
      ]
    },
    {
      "id": "1379176",
      "league": "Premier League",
      "venue": "Etihad Stadium",
      "attendance": null,
      "kickoff": "2026-01-07T19:30:00+00:00",
      "homeTeamId": "manchester-city",
      "awayTeamId": "brighton",
      "score": {
        "home": 1,
        "away": 1
      },
      "status": {
        "state": "FT",
        "halfTimeScore": "1–0"
      },
      "events": [
        {
          "id": "1379176-0",
          "minute": "29'",
          "team": "away",
          "kind": "yellow",
          "player": "Lewis Dunk",
          "assist": "",
          "detail": "",
          "rawType": "Card",
          "rawDetail": "Yellow Card",
          "elapsed": 29,
          "extra": 0
        },
        {
          "id": "1379176-1",
          "minute": "39'",
          "team": "home",
          "kind": "var-pen-confirmed",
          "player": "Jérémy Doku",
          "assist": "",
          "detail": "",
          "rawType": "Var",
          "rawDetail": "Penalty confirmed",
          "elapsed": 39,
          "extra": 0
        },
        {
          "id": "1379176-2",
          "minute": "41'",
          "team": "away",
          "kind": "yellow",
          "player": "Pascal Groß",
          "assist": "",
          "detail": "",
          "rawType": "Card",
          "rawDetail": "Yellow Card",
          "elapsed": 41,
          "extra": 0
        },
        {
          "id": "1379176-3",
          "minute": "41'",
          "team": "home",
          "kind": "goal",
          "player": "E. Haaland",
          "assist": "",
          "detail": "pen",
          "rawType": "Goal",
          "rawDetail": "Penalty",
          "elapsed": 41,
          "extra": 0
        },
        {
          "id": "1379176-4",
          "minute": "53'",
          "team": "away",
          "kind": "yellow",
          "player": "Jan Paul van Hecke",
          "assist": "",
          "detail": "",
          "rawType": "Card",
          "rawDetail": "Yellow Card",
          "elapsed": 53,
          "extra": 0
        },
        {
          "id": "1379176-5",
          "minute": "60'",
          "team": "home",
          "kind": "yellow",
          "player": "Gianluigi Donnarumma",
          "assist": "",
          "detail": "",
          "rawType": "Card",
          "rawDetail": "Yellow Card",
          "elapsed": 60,
          "extra": 0
        },
        {
          "id": "1379176-6",
          "minute": "60'",
          "team": "away",
          "kind": "yellow",
          "player": "Maxim De Cuyper",
          "assist": "",
          "detail": "",
          "rawType": "Card",
          "rawDetail": "Yellow Card",
          "elapsed": 60,
          "extra": 0
        },
        {
          "id": "1379176-7",
          "minute": "60'",
          "team": "away",
          "kind": "goal",
          "player": "K. Mitoma",
          "assist": "Y. Ayari",
          "detail": "",
          "rawType": "Goal",
          "rawDetail": "Normal Goal",
          "elapsed": 60,
          "extra": 0
        },
        {
          "id": "1379176-8",
          "minute": "64'",
          "team": "home",
          "kind": "sub",
          "player": "Nico",
          "assist": "Rodri",
          "inPlayer": "Rodri",
          "outPlayer": "Nico",
          "detail": "",
          "rawType": "subst",
          "rawDetail": "Substitution 1",
          "elapsed": 64,
          "extra": 0
        },
        {
          "id": "1379176-9",
          "minute": "69'",
          "team": "away",
          "kind": "yellow",
          "player": "Kaoru Mitoma",
          "assist": "",
          "detail": "",
          "rawType": "Card",
          "rawDetail": "Yellow Card",
          "elapsed": 69,
          "extra": 0
        },
        {
          "id": "1379176-10",
          "minute": "73'",
          "team": "home",
          "kind": "sub",
          "player": "P. Foden",
          "assist": "R. Cherki",
          "inPlayer": "R. Cherki",
          "outPlayer": "P. Foden",
          "detail": "",
          "rawType": "subst",
          "rawDetail": "Substitution 2",
          "elapsed": 73,
          "extra": 0
        },
        {
          "id": "1379176-11",
          "minute": "73'",
          "team": "home",
          "kind": "sub",
          "player": "N. Ake",
          "assist": "N. O'Reilly",
          "inPlayer": "N. O'Reilly",
          "outPlayer": "N. Ake",
          "detail": "",
          "rawType": "subst",
          "rawDetail": "Substitution 3",
          "elapsed": 73,
          "extra": 0
        },
        {
          "id": "1379176-12",
          "minute": "73'",
          "team": "home",
          "kind": "sub",
          "player": "M. Nunes",
          "assist": "R. Lewis",
          "inPlayer": "R. Lewis",
          "outPlayer": "M. Nunes",
          "detail": "",
          "rawType": "subst",
          "rawDetail": "Substitution 4",
          "elapsed": 73,
          "extra": 0
        },
        {
          "id": "1379176-13",
          "minute": "77'",
          "team": "away",
          "kind": "sub",
          "player": "D. Gomez",
          "assist": "B. Gruda",
          "inPlayer": "B. Gruda",
          "outPlayer": "D. Gomez",
          "detail": "",
          "rawType": "subst",
          "rawDetail": "Substitution 1",
          "elapsed": 77,
          "extra": 0
        },
        {
          "id": "1379176-14",
          "minute": "77'",
          "team": "away",
          "kind": "sub",
          "player": "G. Rutter",
          "assist": "D. Welbeck",
          "inPlayer": "D. Welbeck",
          "outPlayer": "G. Rutter",
          "detail": "",
          "rawType": "subst",
          "rawDetail": "Substitution 2",
          "elapsed": 77,
          "extra": 0
        },
        {
          "id": "1379176-15",
          "minute": "83'",
          "team": "away",
          "kind": "sub",
          "player": "K. Mitoma",
          "assist": "T. Watson",
          "inPlayer": "T. Watson",
          "outPlayer": "K. Mitoma",
          "detail": "",
          "rawType": "subst",
          "rawDetail": "Substitution 3",
          "elapsed": 83,
          "extra": 0
        },
        {
          "id": "1379176-16",
          "minute": "83'",
          "team": "away",
          "kind": "sub",
          "player": "Y. Ayari",
          "assist": "J. Milner",
          "inPlayer": "J. Milner",
          "outPlayer": "Y. Ayari",
          "detail": "",
          "rawType": "subst",
          "rawDetail": "Substitution 4",
          "elapsed": 83,
          "extra": 0
        },
        {
          "id": "1379176-17",
          "minute": "89'",
          "team": "away",
          "kind": "yellow",
          "player": "Tom Watson",
          "assist": "",
          "detail": "",
          "rawType": "Card",
          "rawDetail": "Yellow Card",
          "elapsed": 89,
          "extra": 0
        }
      ]
    },
    {
      "id": "1379173",
      "league": "Premier League",
      "venue": "Selhurst Park",
      "attendance": null,
      "kickoff": "2026-01-07T19:30:00+00:00",
      "homeTeamId": "crystal-palace",
      "awayTeamId": "aston-villa",
      "score": {
        "home": 0,
        "away": 0
      },
      "status": {
        "state": "FT",
        "halfTimeScore": "0–0"
      },
      "events": [
        {
          "id": "1379173-0",
          "minute": "46'",
          "team": "away",
          "kind": "sub",
          "player": "E. Martinez",
          "assist": "M. Bizot",
          "inPlayer": "M. Bizot",
          "outPlayer": "E. Martinez",
          "detail": "",
          "rawType": "subst",
          "rawDetail": "Substitution 1",
          "elapsed": 46,
          "extra": 0
        },
        {
          "id": "1379173-1",
          "minute": "65'",
          "team": "away",
          "kind": "sub",
          "player": "J. Sancho",
          "assist": "E. Buendia",
          "inPlayer": "E. Buendia",
          "outPlayer": "J. Sancho",
          "detail": "",
          "rawType": "subst",
          "rawDetail": "Substitution 2",
          "elapsed": 65,
          "extra": 0
        },
        {
          "id": "1379173-2",
          "minute": "67'",
          "team": "home",
          "kind": "yellow",
          "player": "Brennan Johnson",
          "assist": "",
          "detail": "",
          "rawType": "Card",
          "rawDetail": "Yellow Card",
          "elapsed": 67,
          "extra": 0
        },
        {
          "id": "1379173-3",
          "minute": "73'",
          "team": "away",
          "kind": "sub",
          "player": "J. McGinn",
          "assist": "D. Malen",
          "inPlayer": "D. Malen",
          "outPlayer": "J. McGinn",
          "detail": "",
          "rawType": "subst",
          "rawDetail": "Substitution 3",
          "elapsed": 73,
          "extra": 0
        },
        {
          "id": "1379173-4",
          "minute": "73'",
          "team": "away",
          "kind": "sub",
          "player": "L. Digne",
          "assist": "I. Maatsen",
          "inPlayer": "I. Maatsen",
          "outPlayer": "L. Digne",
          "detail": "",
          "rawType": "subst",
          "rawDetail": "Substitution 4",
          "elapsed": 73,
          "extra": 0
        },
        {
          "id": "1379173-5",
          "minute": "82'",
          "team": "away",
          "kind": "sub",
          "player": "B. Kamara",
          "assist": "L. Bogarde",
          "inPlayer": "L. Bogarde",
          "outPlayer": "B. Kamara",
          "detail": "",
          "rawType": "subst",
          "rawDetail": "Substitution 5",
          "elapsed": 82,
          "extra": 0
        },
        {
          "id": "1379173-6",
          "minute": "83'",
          "team": "home",
          "kind": "yellow",
          "player": "Tyrick Mitchell",
          "assist": "",
          "detail": "",
          "rawType": "Card",
          "rawDetail": "Yellow Card",
          "elapsed": 83,
          "extra": 0
        },
        {
          "id": "1379173-7",
          "minute": "90'",
          "team": "home",
          "kind": "sub",
          "player": "J. Devenny",
          "assist": "B. Sosa",
          "inPlayer": "B. Sosa",
          "outPlayer": "J. Devenny",
          "detail": "",
          "rawType": "subst",
          "rawDetail": "Substitution 1",
          "elapsed": 90,
          "extra": 0
        }
      ]
    },
    {
      "id": "1379171",
      "league": "Premier League",
      "venue": "Brentford Community Stadium",
      "attendance": null,
      "kickoff": "2026-01-07T19:30:00+00:00",
      "homeTeamId": "brentford",
      "awayTeamId": "sunderland",
      "score": {
        "home": 3,
        "away": 0
      },
      "status": {
        "state": "FT",
        "halfTimeScore": "1–0"
      },
      "events": [
        {
          "id": "1379171-0",
          "minute": "30'",
          "team": "home",
          "kind": "goal",
          "player": "I. Thiago",
          "assist": "V. Janelt",
          "detail": "",
          "rawType": "Goal",
          "rawDetail": "Normal Goal",
          "elapsed": 30,
          "extra": 0
        },
        {
          "id": "1379171-1",
          "minute": "43'",
          "team": "home",
          "kind": "yellow",
          "player": "Igor Thiago",
          "assist": "",
          "detail": "",
          "rawType": "Card",
          "rawDetail": "Yellow Card",
          "elapsed": 43,
          "extra": 0
        },
        {
          "id": "1379171-2",
          "minute": "45'",
          "team": "away",
          "kind": "yellow",
          "player": "Trai Hume",
          "assist": "",
          "detail": "",
          "rawType": "Card",
          "rawDetail": "Yellow Card",
          "elapsed": 45,
          "extra": 0
        },
        {
          "id": "1379171-3",
          "minute": "52'",
          "team": "away",
          "kind": "sub",
          "player": "S. Adingra",
          "assist": "R. Mundle",
          "inPlayer": "R. Mundle",
          "outPlayer": "S. Adingra",
          "detail": "",
          "rawType": "subst",
          "rawDetail": "Substitution 1",
          "elapsed": 52,
          "extra": 0
        },
        {
          "id": "1379171-4",
          "minute": "52'",
          "team": "away",
          "kind": "sub",
          "player": "C. Rigg",
          "assist": "E. Mayenda",
          "inPlayer": "E. Mayenda",
          "outPlayer": "C. Rigg",
          "detail": "",
          "rawType": "subst",
          "rawDetail": "Substitution 2",
          "elapsed": 52,
          "extra": 0
        },
        {
          "id": "1379171-5",
          "minute": "61'",
          "team": "home",
          "kind": "sub",
          "player": "K. Lewis-Potter",
          "assist": "M. Damsgaard",
          "inPlayer": "M. Damsgaard",
          "outPlayer": "K. Lewis-Potter",
          "detail": "",
          "rawType": "subst",
          "rawDetail": "Substitution 1",
          "elapsed": 61,
          "extra": 0
        },
        {
          "id": "1379171-6",
          "minute": "63'",
          "team": "home",
          "kind": "yellow",
          "player": "Vitaly Janelt",
          "assist": "",
          "detail": "",
          "rawType": "Card",
          "rawDetail": "Yellow Card",
          "elapsed": 63,
          "extra": 0
        },
        {
          "id": "1379171-7",
          "minute": "65'",
          "team": "home",
          "kind": "goal",
          "player": "I. Thiago",
          "assist": "K. Schade",
          "detail": "",
          "rawType": "Goal",
          "rawDetail": "Normal Goal",
          "elapsed": 65,
          "extra": 0
        },
        {
          "id": "1379171-8",
          "minute": "73'",
          "team": "home",
          "kind": "goal",
          "player": "Y. Yarmolyuk",
          "assist": "N. Collins",
          "detail": "",
          "rawType": "Goal",
          "rawDetail": "Normal Goal",
          "elapsed": 73,
          "extra": 0
        },
        {
          "id": "1379171-9",
          "minute": "76'",
          "team": "home",
          "kind": "sub",
          "player": "M. Jensen",
          "assist": "J. Henderson",
          "inPlayer": "J. Henderson",
          "outPlayer": "M. Jensen",
          "detail": "",
          "rawType": "subst",
          "rawDetail": "Substitution 2",
          "elapsed": 76,
          "extra": 0
        },
        {
          "id": "1379171-10",
          "minute": "79'",
          "team": "away",
          "kind": "sub",
          "player": "D. Ballard",
          "assist": "D. Cirkin",
          "inPlayer": "D. Cirkin",
          "outPlayer": "D. Ballard",
          "detail": "",
          "rawType": "subst",
          "rawDetail": "Substitution 3",
          "elapsed": 79,
          "extra": 0
        },
        {
          "id": "1379171-11",
          "minute": "79'",
          "team": "away",
          "kind": "sub",
          "player": "L. Geertruida",
          "assist": "D. Neil",
          "inPlayer": "D. Neil",
          "outPlayer": "L. Geertruida",
          "detail": "",
          "rawType": "subst",
          "rawDetail": "Substitution 4",
          "elapsed": 79,
          "extra": 0
        },
        {
          "id": "1379171-12",
          "minute": "82'",
          "team": "home",
          "kind": "sub",
          "player": "M. Kayode",
          "assist": "A. Hickey",
          "inPlayer": "A. Hickey",
          "outPlayer": "M. Kayode",
          "detail": "",
          "rawType": "subst",
          "rawDetail": "Substitution 3",
          "elapsed": 82,
          "extra": 0
        },
        {
          "id": "1379171-13",
          "minute": "82'",
          "team": "home",
          "kind": "sub",
          "player": "I. Thiago",
          "assist": "R. Nelson",
          "inPlayer": "R. Nelson",
          "outPlayer": "I. Thiago",
          "detail": "",
          "rawType": "subst",
          "rawDetail": "Substitution 4",
          "elapsed": 82,
          "extra": 0
        },
        {
          "id": "1379171-14",
          "minute": "83'",
          "team": "away",
          "kind": "sub",
          "player": "O. Alderete",
          "assist": "L. O'Nien",
          "inPlayer": "L. O'Nien",
          "outPlayer": "O. Alderete",
          "detail": "",
          "rawType": "subst",
          "rawDetail": "Substitution 5",
          "elapsed": 83,
          "extra": 0
        }
      ]
    },
    {
      "id": "1379177",
      "league": "Premier League",
      "venue": "St. James' Park",
      "attendance": null,
      "kickoff": "2026-01-07T20:15:00+00:00",
      "homeTeamId": "newcastle",
      "awayTeamId": "leeds",
      "score": {
        "home": 4,
        "away": 3
      },
      "status": {
        "state": "FT",
        "halfTimeScore": "1–2"
      },
      "events": [
        {
          "id": "1379177-0",
          "minute": "7'",
          "team": "home",
          "kind": "yellow",
          "player": "Malick Thiaw",
          "assist": "",
          "detail": "",
          "rawType": "Card",
          "rawDetail": "Yellow Card",
          "elapsed": 7,
          "extra": 0
        },
        {
          "id": "1379177-1",
          "minute": "22'",
          "team": "away",
          "kind": "yellow",
          "player": "Dominic Calvert-Lewin",
          "assist": "",
          "detail": "",
          "rawType": "Card",
          "rawDetail": "Yellow Card",
          "elapsed": 22,
          "extra": 0
        },
        {
          "id": "1379177-2",
          "minute": "32'",
          "team": "away",
          "kind": "goal",
          "player": "B. Aaronson",
          "assist": "D. Calvert-Lewin",
          "detail": "",
          "rawType": "Goal",
          "rawDetail": "Normal Goal",
          "elapsed": 32,
          "extra": 0
        },
        {
          "id": "1379177-3",
          "minute": "36'",
          "team": "home",
          "kind": "goal",
          "player": "H. Barnes",
          "assist": "N. Woltemade",
          "detail": "",
          "rawType": "Goal",
          "rawDetail": "Normal Goal",
          "elapsed": 36,
          "extra": 0
        },
        {
          "id": "1379177-4",
          "minute": "45'+6",
          "team": "home",
          "kind": "yellow",
          "player": "Joelinton",
          "assist": "",
          "detail": "",
          "rawType": "Card",
          "rawDetail": "Yellow Card",
          "elapsed": 45,
          "extra": 6
        },
        {
          "id": "1379177-5",
          "minute": "45'+3",
          "team": "home",
          "kind": "yellow",
          "player": "Anthony Gordon",
          "assist": "",
          "detail": "",
          "rawType": "Card",
          "rawDetail": "Yellow Card",
          "elapsed": 45,
          "extra": 3
        },
        {
          "id": "1379177-6",
          "minute": "45'",
          "team": "away",
          "kind": "goal",
          "player": "D. Calvert-Lewin",
          "assist": "",
          "detail": "pen",
          "rawType": "Goal",
          "rawDetail": "Penalty",
          "elapsed": 45,
          "extra": 0
        },
        {
          "id": "1379177-7",
          "minute": "46'",
          "team": "home",
          "kind": "sub",
          "player": "M. Thiaw",
          "assist": "S. Botman",
          "inPlayer": "S. Botman",
          "outPlayer": "M. Thiaw",
          "detail": "",
          "rawType": "subst",
          "rawDetail": "Substitution 1",
          "elapsed": 46,
          "extra": 0
        },
        {
          "id": "1379177-8",
          "minute": "46'",
          "team": "home",
          "kind": "sub",
          "player": "S. Tonali",
          "assist": "V. Livramento",
          "inPlayer": "V. Livramento",
          "outPlayer": "S. Tonali",
          "detail": "",
          "rawType": "subst",
          "rawDetail": "Substitution 2",
          "elapsed": 46,
          "extra": 0
        },
        {
          "id": "1379177-9",
          "minute": "54'",
          "team": "home",
          "kind": "goal",
          "player": "Joelinton",
          "assist": "Bruno Guimaraes",
          "detail": "",
          "rawType": "Goal",
          "rawDetail": "Normal Goal",
          "elapsed": 54,
          "extra": 0
        },
        {
          "id": "1379177-10",
          "minute": "75'",
          "team": "home",
          "kind": "sub",
          "player": "N. Woltemade",
          "assist": "Y. Wissa",
          "inPlayer": "Y. Wissa",
          "outPlayer": "N. Woltemade",
          "detail": "",
          "rawType": "subst",
          "rawDetail": "Substitution 3",
          "elapsed": 75,
          "extra": 0
        },
        {
          "id": "1379177-11",
          "minute": "76'",
          "team": "home",
          "kind": "sub",
          "player": "F. Schar",
          "assist": "J. Ramsey",
          "inPlayer": "J. Ramsey",
          "outPlayer": "F. Schar",
          "detail": "",
          "rawType": "subst",
          "rawDetail": "Substitution 4",
          "elapsed": 76,
          "extra": 0
        },
        {
          "id": "1379177-12",
          "minute": "79'",
          "team": "away",
          "kind": "goal",
          "player": "B. Aaronson",
          "assist": "I. Gruev",
          "detail": "",
          "rawType": "Goal",
          "rawDetail": "Normal Goal",
          "elapsed": 79,
          "extra": 0
        },
        {
          "id": "1379177-13",
          "minute": "80'",
          "team": "away",
          "kind": "sub",
          "player": "A. Stach",
          "assist": "N. Okafor",
          "inPlayer": "N. Okafor",
          "outPlayer": "A. Stach",
          "detail": "",
          "rawType": "subst",
          "rawDetail": "Substitution 1",
          "elapsed": 80,
          "extra": 0
        },
        {
          "id": "1379177-14",
          "minute": "81'",
          "team": "home",
          "kind": "sub",
          "player": "A. Gordon",
          "assist": "J. Murphy",
          "inPlayer": "J. Murphy",
          "outPlayer": "A. Gordon",
          "detail": "",
          "rawType": "subst",
          "rawDetail": "Substitution 5",
          "elapsed": 81,
          "extra": 0
        },
        {
          "id": "1379177-15",
          "minute": "87'",
          "team": "away",
          "kind": "sub",
          "player": "D. Calvert-Lewin",
          "assist": "L. Nmecha",
          "inPlayer": "L. Nmecha",
          "outPlayer": "D. Calvert-Lewin",
          "detail": "",
          "rawType": "subst",
          "rawDetail": "Substitution 2",
          "elapsed": 87,
          "extra": 0
        },
        {
          "id": "1379177-16",
          "minute": "90'+10",
          "team": "away",
          "kind": "yellow",
          "player": "Ethan Ampadu",
          "assist": "",
          "detail": "",
          "rawType": "Card",
          "rawDetail": "Yellow Card",
          "elapsed": 90,
          "extra": 10
        },
        {
          "id": "1379177-17",
          "minute": "90'+7",
          "team": "away",
          "kind": "sub",
          "player": "I. Gruev",
          "assist": "A. Tanaka",
          "inPlayer": "A. Tanaka",
          "outPlayer": "I. Gruev",
          "detail": "",
          "rawType": "subst",
          "rawDetail": "Substitution 3",
          "elapsed": 90,
          "extra": 7
        },
        {
          "id": "1379177-18",
          "minute": "90'+7",
          "team": "away",
          "kind": "sub",
          "player": "J. Rodon",
          "assist": "S. Bornauw",
          "inPlayer": "S. Bornauw",
          "outPlayer": "J. Rodon",
          "detail": "",
          "rawType": "subst",
          "rawDetail": "Substitution 4",
          "elapsed": 90,
          "extra": 7
        },
        {
          "id": "1379177-19",
          "minute": "90'+7",
          "team": "away",
          "kind": "sub",
          "player": "B. Aaronson",
          "assist": "W. Gnonto",
          "inPlayer": "W. Gnonto",
          "outPlayer": "B. Aaronson",
          "detail": "",
          "rawType": "subst",
          "rawDetail": "Substitution 5",
          "elapsed": 90,
          "extra": 7
        },
        {
          "id": "1379177-20",
          "minute": "90'",
          "team": "home",
          "kind": "goal",
          "player": "Bruno Guimaraes",
          "assist": "",
          "detail": "pen",
          "rawType": "Goal",
          "rawDetail": "Penalty",
          "elapsed": 90,
          "extra": 0
        },
        {
          "id": "1379177-21",
          "minute": "90'",
          "team": "home",
          "kind": "goal",
          "player": "H. Barnes",
          "assist": "S. Botman",
          "detail": "",
          "rawType": "Goal",
          "rawDetail": "Normal Goal",
          "elapsed": 90,
          "extra": 0
        }
      ]
    },
    {
      "id": "1379172",
      "league": "Premier League",
      "venue": "Turf Moor",
      "attendance": null,
      "kickoff": "2026-01-07T20:15:00+00:00",
      "homeTeamId": "burnley",
      "awayTeamId": "manchester-united",
      "score": {
        "home": 2,
        "away": 2
      },
      "status": {
        "state": "FT",
        "halfTimeScore": "1–0"
      },
      "events": [
        {
          "id": "1379172-0",
          "minute": "13'",
          "team": "home",
          "kind": "own-goal",
          "player": "A. Heaven",
          "assist": "",
          "detail": "og",
          "rawType": "Goal",
          "rawDetail": "Own Goal",
          "elapsed": 13,
          "extra": 0
        },
        {
          "id": "1379172-1",
          "minute": "41'",
          "team": "home",
          "kind": "yellow",
          "player": "Hannibal Mejbri",
          "assist": "",
          "detail": "",
          "rawType": "Card",
          "rawDetail": "Yellow Card",
          "elapsed": 41,
          "extra": 0
        },
        {
          "id": "1379172-2",
          "minute": "50'",
          "team": "away",
          "kind": "goal",
          "player": "B. Sesko",
          "assist": "B. Fernandes",
          "detail": "",
          "rawType": "Goal",
          "rawDetail": "Normal Goal",
          "elapsed": 50,
          "extra": 0
        },
        {
          "id": "1379172-3",
          "minute": "58'",
          "team": "home",
          "kind": "sub",
          "player": "H. Mejbri",
          "assist": "J. Anthony",
          "inPlayer": "J. Anthony",
          "outPlayer": "H. Mejbri",
          "detail": "",
          "rawType": "subst",
          "rawDetail": "Substitution 1",
          "elapsed": 58,
          "extra": 0
        },
        {
          "id": "1379172-4",
          "minute": "60'",
          "team": "away",
          "kind": "goal",
          "player": "B. Sesko",
          "assist": "P. Dorgu",
          "detail": "",
          "rawType": "Goal",
          "rawDetail": "Normal Goal",
          "elapsed": 60,
          "extra": 0
        },
        {
          "id": "1379172-5",
          "minute": "61'",
          "team": "away",
          "kind": "sub",
          "player": "B. Fernandes",
          "assist": "M. Mount",
          "inPlayer": "M. Mount",
          "outPlayer": "B. Fernandes",
          "detail": "",
          "rawType": "subst",
          "rawDetail": "Substitution 1",
          "elapsed": 61,
          "extra": 0
        },
        {
          "id": "1379172-6",
          "minute": "61'",
          "team": "away",
          "kind": "sub",
          "player": "A. Heaven",
          "assist": "L. Yoro",
          "inPlayer": "L. Yoro",
          "outPlayer": "A. Heaven",
          "detail": "",
          "rawType": "subst",
          "rawDetail": "Substitution 2",
          "elapsed": 61,
          "extra": 0
        },
        {
          "id": "1379172-7",
          "minute": "66'",
          "team": "home",
          "kind": "goal",
          "player": "J. Anthony",
          "assist": "M. Edwards",
          "detail": "",
          "rawType": "Goal",
          "rawDetail": "Normal Goal",
          "elapsed": 66,
          "extra": 0
        },
        {
          "id": "1379172-8",
          "minute": "74'",
          "team": "away",
          "kind": "sub",
          "player": "M. Cunha",
          "assist": "J. Zirkzee",
          "inPlayer": "J. Zirkzee",
          "outPlayer": "M. Cunha",
          "detail": "",
          "rawType": "subst",
          "rawDetail": "Substitution 3",
          "elapsed": 74,
          "extra": 0
        },
        {
          "id": "1379172-9",
          "minute": "74'",
          "team": "away",
          "kind": "sub",
          "player": "Casemiro",
          "assist": "K. Mainoo",
          "inPlayer": "K. Mainoo",
          "outPlayer": "Casemiro",
          "detail": "",
          "rawType": "subst",
          "rawDetail": "Substitution 4",
          "elapsed": 74,
          "extra": 0
        },
        {
          "id": "1379172-10",
          "minute": "76'",
          "team": "home",
          "kind": "sub",
          "player": "A. Broja",
          "assist": "L. Foster",
          "inPlayer": "L. Foster",
          "outPlayer": "A. Broja",
          "detail": "",
          "rawType": "subst",
          "rawDetail": "Substitution 2",
          "elapsed": 76,
          "extra": 0
        },
        {
          "id": "1379172-11",
          "minute": "84'",
          "team": "away",
          "kind": "sub",
          "player": "M. Ugarte",
          "assist": "S. Lacey",
          "inPlayer": "S. Lacey",
          "outPlayer": "M. Ugarte",
          "detail": "",
          "rawType": "subst",
          "rawDetail": "Substitution 5",
          "elapsed": 84,
          "extra": 0
        },
        {
          "id": "1379172-12",
          "minute": "90'+5",
          "team": "home",
          "kind": "yellow",
          "player": "Lyle Foster",
          "assist": "",
          "detail": "",
          "rawType": "Card",
          "rawDetail": "Yellow Card",
          "elapsed": 90,
          "extra": 5
        },
        {
          "id": "1379172-13",
          "minute": "90'+2",
          "team": "home",
          "kind": "sub",
          "player": "M. Edwards",
          "assist": "O. Sonne",
          "inPlayer": "O. Sonne",
          "outPlayer": "M. Edwards",
          "detail": "",
          "rawType": "subst",
          "rawDetail": "Substitution 3",
          "elapsed": 90,
          "extra": 2
        }
      ]
    },
    {
      "id": "1379169",
      "league": "Premier League",
      "venue": "Emirates Stadium",
      "attendance": null,
      "kickoff": "2026-01-08T20:00:00+00:00",
      "homeTeamId": "arsenal",
      "awayTeamId": "liverpool",
      "score": {
        "home": 0,
        "away": 0
      },
      "status": {
        "state": "FT",
        "halfTimeScore": "0–0"
      },
      "events": [
        {
          "id": "1379169-0",
          "minute": "12'",
          "team": "home",
          "kind": "yellow",
          "player": "Leandro Trossard",
          "assist": "",
          "detail": "",
          "rawType": "Card",
          "rawDetail": "Yellow Card",
          "elapsed": 12,
          "extra": 0
        },
        {
          "id": "1379169-1",
          "minute": "57'",
          "team": "home",
          "kind": "sub",
          "player": "P. Hincapie",
          "assist": "M. Lewis-Skelly",
          "inPlayer": "M. Lewis-Skelly",
          "outPlayer": "P. Hincapie",
          "detail": "",
          "rawType": "subst",
          "rawDetail": "Substitution 1",
          "elapsed": 57,
          "extra": 0
        },
        {
          "id": "1379169-2",
          "minute": "64'",
          "team": "home",
          "kind": "sub",
          "player": "V. Gyökeres",
          "assist": "Gabriel Jesus",
          "inPlayer": "Gabriel Jesus",
          "outPlayer": "V. Gyökeres",
          "detail": "",
          "rawType": "subst",
          "rawDetail": "Substitution 2",
          "elapsed": 64,
          "extra": 0
        },
        {
          "id": "1379169-3",
          "minute": "64'",
          "team": "home",
          "kind": "sub",
          "player": "L. Trossard",
          "assist": "G. Martinelli",
          "inPlayer": "G. Martinelli",
          "outPlayer": "L. Trossard",
          "detail": "",
          "rawType": "subst",
          "rawDetail": "Substitution 3",
          "elapsed": 64,
          "extra": 0
        },
        {
          "id": "1379169-4",
          "minute": "78'",
          "team": "home",
          "kind": "sub",
          "player": "M. Odegaard",
          "assist": "E. Eze",
          "inPlayer": "E. Eze",
          "outPlayer": "M. Odegaard",
          "detail": "",
          "rawType": "subst",
          "rawDetail": "Substitution 4",
          "elapsed": 78,
          "extra": 0
        },
        {
          "id": "1379169-5",
          "minute": "78'",
          "team": "home",
          "kind": "sub",
          "player": "B. Saka",
          "assist": "N. Madueke",
          "inPlayer": "N. Madueke",
          "outPlayer": "B. Saka",
          "detail": "",
          "rawType": "subst",
          "rawDetail": "Substitution 5",
          "elapsed": 78,
          "extra": 0
        },
        {
          "id": "1379169-6",
          "minute": "90'+3",
          "team": "home",
          "kind": "yellow",
          "player": "Gabriel Martinelli",
          "assist": "",
          "detail": "",
          "rawType": "Card",
          "rawDetail": "Yellow Card",
          "elapsed": 90,
          "extra": 3
        },
        {
          "id": "1379169-7",
          "minute": "90'+3",
          "team": "away",
          "kind": "yellow",
          "player": "Ibrahima Konaté",
          "assist": "",
          "detail": "",
          "rawType": "Card",
          "rawDetail": "Yellow Card",
          "elapsed": 90,
          "extra": 3
        },
        {
          "id": "1379169-8",
          "minute": "90'",
          "team": "away",
          "kind": "yellow",
          "player": "Alexis Mac Allister",
          "assist": "",
          "detail": "",
          "rawType": "Card",
          "rawDetail": "Yellow Card",
          "elapsed": 90,
          "extra": 0
        },
        {
          "id": "1379169-9",
          "minute": "90'+5",
          "team": "away",
          "kind": "sub",
          "player": "C. Bradley",
          "assist": "J. Gomez",
          "inPlayer": "J. Gomez",
          "outPlayer": "C. Bradley",
          "detail": "",
          "rawType": "subst",
          "rawDetail": "Substitution 1",
          "elapsed": 90,
          "extra": 5
        }
      ]
    }
  ]
}