{
  "season": 2025,
  "round": 37,
  "matches": [
    {
      "id": "1379336",
      "league": "Premier League",
      "venue": "Old Trafford",
      "attendance": null,
      "kickoff": "2026-05-17T14:00:00+00:00",
      "homeTeamId": "manchester-united",
      "awayTeamId": "nottingham-forest",
      "score": {
        "home": 0,
        "away": 0
      },
      "status": {
        "state": "NS",
        "halfTimeScore": ""
      },
      "events": []
    },
    {
      "id": "1379337",
      "league": "Premier League",
      "venue": "St. James' Park",
      "attendance": null,
      "kickoff": "2026-05-17T14:00:00+00:00",
      "homeTeamId": "newcastle",
      "awayTeamId": "west-ham",
      "score": {
        "home": 0,
        "away": 0
      },
      "status": {
        "state": "NS",
        "halfTimeScore": ""
      },
      "events": []
    },
    {
      "id": "1379331",
      "league": "Premier League",
      "venue": "Vitality Stadium",
      "attendance": null,
      "kickoff": "2026-05-17T14:00:00+00:00",
      "homeTeamId": "bournemouth",
      "awayTeamId": "manchester-city",
      "score": {
        "home": 0,
        "away": 0
      },
      "status": {
        "state": "NS",
        "halfTimeScore": ""
      },
      "events": []
    },
    {
      "id": "1379338",
      "league": "Premier League",
      "venue": "Molineux Stadium",
      "attendance": null,
      "kickoff": "2026-05-17T14:00:00+00:00",
      "homeTeamId": "wolves",
      "awayTeamId": "fulham",
      "score": {
        "home": 0,
        "away": 0
      },
      "status": {
        "state": "NS",
        "halfTimeScore": ""
      },
      "events": []
    },
    {
      "id": "1379329",
      "league": "Premier League",
      "venue": "Emirates Stadium",
      "attendance": null,
      "kickoff": "2026-05-17T14:00:00+00:00",
      "homeTeamId": "arsenal",
      "awayTeamId": "burnley",
      "score": {
        "home": 0,
        "away": 0
      },
      "status": {
        "state": "NS",
        "halfTimeScore": ""
      },
      "events": []
    },
    {
      "id": "1379334",
      "league": "Premier League",
      "venue": "Hill Dickinson Stadium",
      "attendance": null,
      "kickoff": "2026-05-17T14:00:00+00:00",
      "homeTeamId": "everton",
      "awayTeamId": "sunderland",
      "score": {
        "home": 0,
        "away": 0
      },
      "status": {
        "state": "NS",
        "halfTimeScore": ""
      },
      "events": []
    },
    {
      "id": "1379333",
      "league": "Premier League",
      "venue": "Stamford Bridge",
      "attendance": null,
      "kickoff": "2026-05-17T14:00:00+00:00",
      "homeTeamId": "chelsea",
      "awayTeamId": "tottenham",
      "score": {
        "home": 0,
        "away": 0
      },
      "status": {
        "state": "NS",
        "halfTimeScore": ""
      },
      "events": []
    },
    {
      "id": "1379332",
      "league": "Premier League",
      "venue": "Brentford Community Stadium",
      "attendance": null,
      "kickoff": "2026-05-17T14:00:00+00:00",
      "homeTeamId": "brentford",
      "awayTeamId": "crystal-palace",
      "score": {
        "home": 0,
        "away": 0
      },
      "status": {
        "state": "NS",
        "halfTimeScore": ""
      },
      "events": []
    },
    {
      "id": "1379335",
      "league": "Premier League",
      "venue": "Elland Road",
      "attendance": null,
      "kickoff": "2026-05-17T14:00:00+00:00",
      "homeTeamId": "leeds",
      "awayTeamId": "brighton",
      "score": {
        "home": 0,
        "away": 0
      },
      "status": {
        "state": "NS",
        "halfTimeScore": ""
      },
      "events": []
    },
    {
      "id": "1379330",
      "league": "Premier League",
      "venue": "Villa Park",
      "attendance": null,
      "kickoff": "2026-05-17T14:00:00+00:00",
      "homeTeamId": "aston-villa",
      "awayTeamId": "liverpool",
      "score": {
        "home": 0,
        "away": 0
      },
      "status": {
        "state": "NS",
        "halfTimeScore": ""
      },
      "events": []
    }
  ]
}